setup.py
DFStyler/Library.py
DFStyler/__init__.py
dataframestyler-0.0.1.dist-info/METADATA
dataframestyler-0.0.1.dist-info/WHEEL
dataframestyler-0.0.1.dist-info/licenses/LICENSE.txt
dataframestyler-0.0.1.dist-info/RECORD
